LICENSE
README.md
pyproject.toml
setup.py
teyxos.webhooks.egg-info/PKG-INFO
teyxos.webhooks.egg-info/SOURCES.txt
teyxos.webhooks.egg-info/dependency_links.txt
teyxos.webhooks.egg-info/requires.txt
teyxos.webhooks.egg-info/top_level.txt
webhooks/__init__.py
webhooks/__main__.py
webhooks/create.py
webhooks/webhooks.py