Metadata-Version: 2.1
Name: teyxos.webhooks
Version: 1.0.0
Summary: A simple discord-webhook tool for python
Home-page: UNKNOWN
Author: Teyxos
Author-email: teyxosesp@gmail.com
License: MIT
Platform: UNKNOWN
Classifier: License :: OSI Approved :: MIT License
Classifier: Programming Language :: Python :: 3
License-File: LICENSE
